seqsum/__init__.py
seqsum/cli.py
seqsum/lib.py
seqsum-0.2.0.dist-info/entry_points.txt
seqsum-0.2.0.dist-info/LICENSE
seqsum-0.2.0.dist-info/WHEEL
seqsum-0.2.0.dist-info/METADATA
seqsum-0.2.0.dist-info/RECORD
